fermi_contours/__init__.py
fermi_contours/__main__.py
fermi_contours/marching_squares.py
fermi_contours/py.typed
fermi_contours-0.1.4.dist-info/entry_points.txt
fermi_contours-0.1.4.dist-info/LICENSE
fermi_contours-0.1.4.dist-info/WHEEL
fermi_contours-0.1.4.dist-info/METADATA
fermi_contours-0.1.4.dist-info/RECORD
