Metadata-Version: 2.1
Name: fermi-contours
Version: 0.1.4
Summary: Fermi Contours
Home-page: https://github.com/piskunow/fermi-contours
License: 2-Clause BSD License
Author: Pablo Piskunow
Author-email: pablo@piskunow.com
Requires-Python: >=3.9,<4.0
Classifier: Development Status :: 1 - Planning
Classifier: License :: Other/Proprietary License
Classifier: Programming Language :: Python :: 3
Classifier: Programming Language :: Python :: 3.9
Classifier: Programming Language :: Python :: 3.10
Classifier: Programming Language :: Python :: 3.11
Requires-Dist: certifi (>=2023.07.22,<2024.0.0)
Requires-Dist: click (>=8.0.1)
Requires-Dist: dparse (>=0.6.2,<0.7.0)
Requires-Dist: gitpython (>=3.1.35,<4.0.0)
Requires-Dist: ipython (>=8.10.0,<9.0.0)
Requires-Dist: markdown-it-py (>=2.2.0,<3.0.0)
Requires-Dist: nbsphinx (>=0.9.3,<0.10.0)
Requires-Dist: numpy (>=1.23.5,<2.0.0)
Requires-Dist: pygments (>=2.15.0,<3.0.0)
Requires-Dist: requests (>=2.31.0,<3.0.0)
Requires-Dist: tornado (>=6.3.2,<7.0.0)
Requires-Dist: urllib3 (>=1.26.17,<2.0.0)
Project-URL: Changelog, https://github.com/piskunow/fermi-contours/releases
Project-URL: Documentation, https://fermi-contours.readthedocs.io
Project-URL: Repository, https://github.com/piskunow/fermi-contours
